[
  {
    "fetch_id": "92088713",
    "source_id": "bhaskar_biz_rss",
    "start_time_ist": "03-03-2026 15:15 IST",
    "end_time_ist": "03-03-2026 15:15 IST",
    "records_fetched": 0,
    "failures": 0,
    "error_message": "",
    "status": "OK"
  },
  {
    "fetch_id": "daedcb84",
    "source_id": "rigzone_rss",
    "start_time_ist": "03-03-2026 15:15 IST",
    "end_time_ist": "03-03-2026 15:15 IST",
    "records_fetched": 0,
    "failures": 0,
    "error_message": "",
    "status": "OK"
  },
  {
    "fetch_id": "54a56064",
    "source_id": "reuters_biz_rss",
    "start_time_ist": "03-03-2026 15:15 IST",
    "end_time_ist": "03-03-2026 15:15 IST",
    "records_fetched": 0,
    "failures": 1,
    "error_message": "<urlopen error [Errno 11001] getaddrinfo failed>",
    "status": "Fail"
  },
  {
    "fetch_id": "cc16e005",
    "source_id": "cnbc_energy_rss",
    "start_time_ist": "03-03-2026 15:15 IST",
    "end_time_ist": "03-03-2026 15:15 IST",
    "records_fetched": 0,
    "failures": 0,
    "error_message": "",
    "status": "OK"
  },
  {
    "fetch_id": "9958d3f3",
    "source_id": "mw_commodities_rss",
    "start_time_ist": "03-03-2026 15:15 IST",
    "end_time_ist": "03-03-2026 15:15 IST",
    "records_fetched": 0,
    "failures": 1,
    "error_message": "HTTP Error 403: Forbidden",
    "status": "Fail"
  },
  {
    "fetch_id": "1f967fb4",
    "source_id": "pib_infra_rss",
    "start_time_ist": "03-03-2026 15:15 IST",
    "end_time_ist": "03-03-2026 15:15 IST",
    "records_fetched": 0,
    "failures": 0,
    "error_message": "",
    "status": "OK"
  },
  {
    "fetch_id": "6c40cdc7",
    "source_id": "et_infra_rss",
    "start_time_ist": "03-03-2026 15:15 IST",
    "end_time_ist": "03-03-2026 15:15 IST",
    "records_fetched": 0,
    "failures": 0,
    "error_message": "",
    "status": "OK"
  },
  {
    "fetch_id": "f69abe0e",
    "source_id": "bs_economy_rss",
    "start_time_ist": "03-03-2026 15:15 IST",
    "end_time_ist": "03-03-2026 15:15 IST",
    "records_fetched": 0,
    "failures": 1,
    "error_message": "HTTP Error 403: Forbidden",
    "status": "Fail"
  },
  {
    "fetch_id": "89d4485c",
    "source_id": "mint_rss",
    "start_time_ist": "03-03-2026 15:15 IST",
    "end_time_ist": "03-03-2026 15:15 IST",
    "records_fetched": 0,
    "failures": 0,
    "error_message": "",
    "status": "OK"
  },
  {
    "fetch_id": "e44d30f0",
    "source_id": "ndtv_hindi_rss",
    "start_time_ist": "03-03-2026 15:15 IST",
    "end_time_ist": "03-03-2026 15:15 IST",
    "records_fetched": 0,
    "failures": 1,
    "error_message": "HTTP Error 403: Forbidden",
    "status": "Fail"
  },
  {
    "fetch_id": "43a4beff",
    "source_id": "bhaskar_biz_rss",
    "start_time_ist": "03-03-2026 15:15 IST",
    "end_time_ist": "03-03-2026 15:15 IST",
    "records_fetched": 0,
    "failures": 0,
    "error_message": "",
    "status": "OK"
  },
  {
    "fetch_id": "188585b8",
    "source_id": "oilprice_rss",
    "start_time_ist": "03-03-2026 15:23 IST",
    "end_time_ist": "03-03-2026 15:23 IST",
    "records_fetched": 0,
    "failures": 0,
    "error_message": "",
    "status": "OK"
  },
  {
    "fetch_id": "5795f019",
    "source_id": "eia_rss",
    "start_time_ist": "03-03-2026 15:23 IST",
    "end_time_ist": "03-03-2026 15:23 IST",
    "records_fetched": 0,
    "failures": 0,
    "error_message": "",
    "status": "OK"
  },
  {
    "fetch_id": "1728677c",
    "source_id": "rigzone_rss",
    "start_time_ist": "03-03-2026 15:23 IST",
    "end_time_ist": "03-03-2026 15:23 IST",
    "records_fetched": 0,
    "failures": 0,
    "error_message": "",
    "status": "OK"
  },
  {
    "fetch_id": "447ad3f4",
    "source_id": "reuters_biz_rss",
    "start_time_ist": "03-03-2026 15:23 IST",
    "end_time_ist": "03-03-2026 15:23 IST",
    "records_fetched": 0,
    "failures": 1,
    "error_message": "<urlopen error [Errno 11001] getaddrinfo failed>",
    "status": "Fail"
  },
  {
    "fetch_id": "60292e1b",
    "source_id": "cnbc_energy_rss",
    "start_time_ist": "03-03-2026 15:23 IST",
    "end_time_ist": "03-03-2026 15:23 IST",
    "records_fetched": 0,
    "failures": 0,
    "error_message": "",
    "status": "OK"
  },
  {
    "fetch_id": "b0309968",
    "source_id": "mw_commodities_rss",
    "start_time_ist": "03-03-2026 15:23 IST",
    "end_time_ist": "03-03-2026 15:23 IST",
    "records_fetched": 0,
    "failures": 1,
    "error_message": "HTTP Error 403: Forbidden",
    "status": "Fail"
  },
  {
    "fetch_id": "91a9d30b",
    "source_id": "pib_infra_rss",
    "start_time_ist": "03-03-2026 15:23 IST",
    "end_time_ist": "03-03-2026 15:23 IST",
    "records_fetched": 0,
    "failures": 0,
    "error_message": "",
    "status": "OK"
  },
  {
    "fetch_id": "2596148b",
    "source_id": "et_infra_rss",
    "start_time_ist": "03-03-2026 15:23 IST",
    "end_time_ist": "03-03-2026 15:23 IST",
    "records_fetched": 0,
    "failures": 0,
    "error_message": "",
    "status": "OK"
  },
  {
    "fetch_id": "00bd1529",
    "source_id": "bs_economy_rss",
    "start_time_ist": "03-03-2026 15:23 IST",
    "end_time_ist": "03-03-2026 15:23 IST",
    "records_fetched": 0,
    "failures": 1,
    "error_message": "HTTP Error 403: Forbidden",
    "status": "Fail"
  },
  {
    "fetch_id": "950a61b5",
    "source_id": "mint_rss",
    "start_time_ist": "03-03-2026 15:23 IST",
    "end_time_ist": "03-03-2026 15:23 IST",
    "records_fetched": 2,
    "failures": 0,
    "error_message": "",
    "status": "OK"
  },
  {
    "fetch_id": "bf24851c",
    "source_id": "ndtv_hindi_rss",
    "start_time_ist": "03-03-2026 15:23 IST",
    "end_time_ist": "03-03-2026 15:23 IST",
    "records_fetched": 0,
    "failures": 1,
    "error_message": "HTTP Error 403: Forbidden",
    "status": "Fail"
  },
  {
    "fetch_id": "27f1f4c2",
    "source_id": "bhaskar_biz_rss",
    "start_time_ist": "03-03-2026 15:23 IST",
    "end_time_ist": "03-03-2026 15:23 IST",
    "records_fetched": 0,
    "failures": 0,
    "error_message": "",
    "status": "OK"
  },
  {
    "fetch_id": "dca69b3b",
    "source_id": "oilprice_rss",
    "start_time_ist": "03-03-2026 15:24 IST",
    "end_time_ist": "03-03-2026 15:24 IST",
    "records_fetched": 0,
    "failures": 0,
    "error_message": "",
    "status": "OK"
  },
  {
    "fetch_id": "00f515d7",
    "source_id": "eia_rss",
    "start_time_ist": "03-03-2026 15:24 IST",
    "end_time_ist": "03-03-2026 15:25 IST",
    "records_fetched": 0,
    "failures": 0,
    "error_message": "",
    "status": "OK"
  },
  {
    "fetch_id": "db076dee",
    "source_id": "rigzone_rss",
    "start_time_ist": "03-03-2026 15:25 IST",
    "end_time_ist": "03-03-2026 15:25 IST",
    "records_fetched": 0,
    "failures": 0,
    "error_message": "",
    "status": "OK"
  },
  {
    "fetch_id": "d414570e",
    "source_id": "reuters_biz_rss",
    "start_time_ist": "03-03-2026 15:25 IST",
    "end_time_ist": "03-03-2026 15:25 IST",
    "records_fetched": 0,
    "failures": 1,
    "error_message": "<urlopen error [Errno 11001] getaddrinfo failed>",
    "status": "Fail"
  },
  {
    "fetch_id": "07293bef",
    "source_id": "cnbc_energy_rss",
    "start_time_ist": "03-03-2026 15:25 IST",
    "end_time_ist": "03-03-2026 15:25 IST",
    "records_fetched": 0,
    "failures": 0,
    "error_message": "",
    "status": "OK"
  },
  {
    "fetch_id": "f3ddab52",
    "source_id": "mw_commodities_rss",
    "start_time_ist": "03-03-2026 15:25 IST",
    "end_time_ist": "03-03-2026 15:25 IST",
    "records_fetched": 0,
    "failures": 1,
    "error_message": "HTTP Error 403: Forbidden",
    "status": "Fail"
  },
  {
    "fetch_id": "f561aa14",
    "source_id": "pib_infra_rss",
    "start_time_ist": "03-03-2026 15:25 IST",
    "end_time_ist": "03-03-2026 15:25 IST",
    "records_fetched": 0,
    "failures": 0,
    "error_message": "",
    "status": "OK"
  },
  {
    "fetch_id": "61d7ceb3",
    "source_id": "et_infra_rss",
    "start_time_ist": "03-03-2026 15:25 IST",
    "end_time_ist": "03-03-2026 15:25 IST",
    "records_fetched": 0,
    "failures": 0,
    "error_message": "",
    "status": "OK"
  },
  {
    "fetch_id": "32de3fba",
    "source_id": "bs_economy_rss",
    "start_time_ist": "03-03-2026 15:25 IST",
    "end_time_ist": "03-03-2026 15:25 IST",
    "records_fetched": 0,
    "failures": 1,
    "error_message": "HTTP Error 403: Forbidden",
    "status": "Fail"
  },
  {
    "fetch_id": "6b47dbcf",
    "source_id": "mint_rss",
    "start_time_ist": "03-03-2026 15:25 IST",
    "end_time_ist": "03-03-2026 15:25 IST",
    "records_fetched": 0,
    "failures": 0,
    "error_message": "",
    "status": "OK"
  },
  {
    "fetch_id": "60a38d74",
    "source_id": "ndtv_hindi_rss",
    "start_time_ist": "03-03-2026 15:25 IST",
    "end_time_ist": "03-03-2026 15:25 IST",
    "records_fetched": 0,
    "failures": 1,
    "error_message": "HTTP Error 403: Forbidden",
    "status": "Fail"
  },
  {
    "fetch_id": "35aecde0",
    "source_id": "oilprice_rss",
    "start_time_ist": "03-03-2026 15:25 IST",
    "end_time_ist": "03-03-2026 15:25 IST",
    "records_fetched": 0,
    "failures": 0,
    "error_message": "",
    "status": "OK"
  },
  {
    "fetch_id": "3452aeb9",
    "source_id": "bhaskar_biz_rss",
    "start_time_ist": "03-03-2026 15:25 IST",
    "end_time_ist": "03-03-2026 15:25 IST",
    "records_fetched": 0,
    "failures": 0,
    "error_message": "",
    "status": "OK"
  },
  {
    "fetch_id": "81556e60",
    "source_id": "eia_rss",
    "start_time_ist": "03-03-2026 15:25 IST",
    "end_time_ist": "03-03-2026 15:25 IST",
    "records_fetched": 0,
    "failures": 0,
    "error_message": "",
    "status": "OK"
  },
  {
    "fetch_id": "1f593a93",
    "source_id": "rigzone_rss",
    "start_time_ist": "03-03-2026 15:25 IST",
    "end_time_ist": "03-03-2026 15:25 IST",
    "records_fetched": 0,
    "failures": 0,
    "error_message": "",
    "status": "OK"
  },
  {
    "fetch_id": "924a427b",
    "source_id": "reuters_biz_rss",
    "start_time_ist": "03-03-2026 15:25 IST",
    "end_time_ist": "03-03-2026 15:25 IST",
    "records_fetched": 0,
    "failures": 1,
    "error_message": "<urlopen error [Errno 11001] getaddrinfo failed>",
    "status": "Fail"
  },
  {
    "fetch_id": "d8acc805",
    "source_id": "cnbc_energy_rss",
    "start_time_ist": "03-03-2026 15:25 IST",
    "end_time_ist": "03-03-2026 15:25 IST",
    "records_fetched": 0,
    "failures": 0,
    "error_message": "",
    "status": "OK"
  },
  {
    "fetch_id": "e8e1fed4",
    "source_id": "oilprice_rss",
    "start_time_ist": "03-03-2026 15:25 IST",
    "end_time_ist": "03-03-2026 15:25 IST",
    "records_fetched": 0,
    "failures": 0,
    "error_message": "",
    "status": "OK"
  },
  {
    "fetch_id": "c5acf400",
    "source_id": "mw_commodities_rss",
    "start_time_ist": "03-03-2026 15:25 IST",
    "end_time_ist": "03-03-2026 15:25 IST",
    "records_fetched": 0,
    "failures": 1,
    "error_message": "HTTP Error 403: Forbidden",
    "status": "Fail"
  },
  {
    "fetch_id": "0b80cd1b",
    "source_id": "pib_infra_rss",
    "start_time_ist": "03-03-2026 15:25 IST",
    "end_time_ist": "03-03-2026 15:25 IST",
    "records_fetched": 0,
    "failures": 0,
    "error_message": "",
    "status": "OK"
  },
  {
    "fetch_id": "2db2534c",
    "source_id": "et_infra_rss",
    "start_time_ist": "03-03-2026 15:25 IST",
    "end_time_ist": "03-03-2026 15:25 IST",
    "records_fetched": 0,
    "failures": 0,
    "error_message": "",
    "status": "OK"
  },
  {
    "fetch_id": "20667e17",
    "source_id": "bs_economy_rss",
    "start_time_ist": "03-03-2026 15:25 IST",
    "end_time_ist": "03-03-2026 15:25 IST",
    "records_fetched": 0,
    "failures": 1,
    "error_message": "HTTP Error 403: Forbidden",
    "status": "Fail"
  },
  {
    "fetch_id": "8e439494",
    "source_id": "mint_rss",
    "start_time_ist": "03-03-2026 15:25 IST",
    "end_time_ist": "03-03-2026 15:25 IST",
    "records_fetched": 0,
    "failures": 0,
    "error_message": "",
    "status": "OK"
  },
  {
    "fetch_id": "645af35f",
    "source_id": "ndtv_hindi_rss",
    "start_time_ist": "03-03-2026 15:25 IST",
    "end_time_ist": "03-03-2026 15:25 IST",
    "records_fetched": 0,
    "failures": 1,
    "error_message": "HTTP Error 403: Forbidden",
    "status": "Fail"
  },
  {
    "fetch_id": "8b9f849f",
    "source_id": "bhaskar_biz_rss",
    "start_time_ist": "03-03-2026 15:25 IST",
    "end_time_ist": "03-03-2026 15:25 IST",
    "records_fetched": 0,
    "failures": 0,
    "error_message": "",
    "status": "OK"
  },
  {
    "fetch_id": "69d675cb",
    "source_id": "eia_rss",
    "start_time_ist": "03-03-2026 15:25 IST",
    "end_time_ist": "03-03-2026 15:25 IST",
    "records_fetched": 0,
    "failures": 0,
    "error_message": "",
    "status": "OK"
  },
  {
    "fetch_id": "ddbb8ce2",
    "source_id": "rigzone_rss",
    "start_time_ist": "03-03-2026 15:25 IST",
    "end_time_ist": "03-03-2026 15:25 IST",
    "records_fetched": 0,
    "failures": 0,
    "error_message": "",
    "status": "OK"
  },
  {
    "fetch_id": "cd96896f",
    "source_id": "reuters_biz_rss",
    "start_time_ist": "03-03-2026 15:25 IST",
    "end_time_ist": "03-03-2026 15:25 IST",
    "records_fetched": 0,
    "failures": 1,
    "error_message": "<urlopen error [Errno 11001] getaddrinfo failed>",
    "status": "Fail"
  },
  {
    "fetch_id": "db031d38",
    "source_id": "cnbc_energy_rss",
    "start_time_ist": "03-03-2026 15:25 IST",
    "end_time_ist": "03-03-2026 15:25 IST",
    "records_fetched": 0,
    "failures": 0,
    "error_message": "",
    "status": "OK"
  },
  {
    "fetch_id": "c743e59d",
    "source_id": "mw_commodities_rss",
    "start_time_ist": "03-03-2026 15:25 IST",
    "end_time_ist": "03-03-2026 15:25 IST",
    "records_fetched": 0,
    "failures": 1,
    "error_message": "HTTP Error 403: Forbidden",
    "status": "Fail"
  },
  {
    "fetch_id": "7219f9ed",
    "source_id": "pib_infra_rss",
    "start_time_ist": "03-03-2026 15:25 IST",
    "end_time_ist": "03-03-2026 15:25 IST",
    "records_fetched": 0,
    "failures": 0,
    "error_message": "",
    "status": "OK"
  },
  {
    "fetch_id": "c130f16d",
    "source_id": "et_infra_rss",
    "start_time_ist": "03-03-2026 15:25 IST",
    "end_time_ist": "03-03-2026 15:25 IST",
    "records_fetched": 0,
    "failures": 0,
    "error_message": "",
    "status": "OK"
  },
  {
    "fetch_id": "80c4bd11",
    "source_id": "bs_economy_rss",
    "start_time_ist": "03-03-2026 15:25 IST",
    "end_time_ist": "03-03-2026 15:25 IST",
    "records_fetched": 0,
    "failures": 1,
    "error_message": "HTTP Error 403: Forbidden",
    "status": "Fail"
  },
  {
    "fetch_id": "c4e7463c",
    "source_id": "mint_rss",
    "start_time_ist": "03-03-2026 15:25 IST",
    "end_time_ist": "03-03-2026 15:25 IST",
    "records_fetched": 0,
    "failures": 0,
    "error_message": "",
    "status": "OK"
  },
  {
    "fetch_id": "6894ed5b",
    "source_id": "ndtv_hindi_rss",
    "start_time_ist": "03-03-2026 15:25 IST",
    "end_time_ist": "03-03-2026 15:25 IST",
    "records_fetched": 0,
    "failures": 1,
    "error_message": "HTTP Error 403: Forbidden",
    "status": "Fail"
  },
  {
    "fetch_id": "8e4dae86",
    "source_id": "bhaskar_biz_rss",
    "start_time_ist": "03-03-2026 15:25 IST",
    "end_time_ist": "03-03-2026 15:25 IST",
    "records_fetched": 1,
    "failures": 0,
    "error_message": "",
    "status": "OK"
  },
  {
    "fetch_id": "4d789c80",
    "source_id": "oilprice_rss",
    "start_time_ist": "03-03-2026 15:33 IST",
    "end_time_ist": "03-03-2026 15:34 IST",
    "records_fetched": 0,
    "failures": 0,
    "error_message": "",
    "status": "OK"
  },
  {
    "fetch_id": "39b33c09",
    "source_id": "eia_rss",
    "start_time_ist": "03-03-2026 15:34 IST",
    "end_time_ist": "03-03-2026 15:34 IST",
    "records_fetched": 0,
    "failures": 0,
    "error_message": "",
    "status": "OK"
  },
  {
    "fetch_id": "b5825504",
    "source_id": "rigzone_rss",
    "start_time_ist": "03-03-2026 15:34 IST",
    "end_time_ist": "03-03-2026 15:34 IST",
    "records_fetched": 0,
    "failures": 0,
    "error_message": "",
    "status": "OK"
  },
  {
    "fetch_id": "76564d21",
    "source_id": "reuters_biz_rss",
    "start_time_ist": "03-03-2026 15:34 IST",
    "end_time_ist": "03-03-2026 15:34 IST",
    "records_fetched": 0,
    "failures": 1,
    "error_message": "<urlopen error [Errno 11001] getaddrinfo failed>",
    "status": "Fail"
  },
  {
    "fetch_id": "a12872db",
    "source_id": "cnbc_energy_rss",
    "start_time_ist": "03-03-2026 15:34 IST",
    "end_time_ist": "03-03-2026 15:34 IST",
    "records_fetched": 0,
    "failures": 0,
    "error_message": "",
    "status": "OK"
  },
  {
    "fetch_id": "7f1a0ace",
    "source_id": "mw_commodities_rss",
    "start_time_ist": "03-03-2026 15:34 IST",
    "end_time_ist": "03-03-2026 15:34 IST",
    "records_fetched": 0,
    "failures": 1,
    "error_message": "HTTP Error 403: Forbidden",
    "status": "Fail"
  },
  {
    "fetch_id": "59656231",
    "source_id": "pib_infra_rss",
    "start_time_ist": "03-03-2026 15:34 IST",
    "end_time_ist": "03-03-2026 15:34 IST",
    "records_fetched": 0,
    "failures": 0,
    "error_message": "",
    "status": "OK"
  },
  {
    "fetch_id": "3675c469",
    "source_id": "et_infra_rss",
    "start_time_ist": "03-03-2026 15:34 IST",
    "end_time_ist": "03-03-2026 15:34 IST",
    "records_fetched": 0,
    "failures": 0,
    "error_message": "",
    "status": "OK"
  },
  {
    "fetch_id": "762e05ec",
    "source_id": "bs_economy_rss",
    "start_time_ist": "03-03-2026 15:34 IST",
    "end_time_ist": "03-03-2026 15:34 IST",
    "records_fetched": 0,
    "failures": 1,
    "error_message": "HTTP Error 403: Forbidden",
    "status": "Fail"
  },
  {
    "fetch_id": "5be5a02c",
    "source_id": "mint_rss",
    "start_time_ist": "03-03-2026 15:34 IST",
    "end_time_ist": "03-03-2026 15:34 IST",
    "records_fetched": 1,
    "failures": 0,
    "error_message": "",
    "status": "OK"
  },
  {
    "fetch_id": "ba855ec4",
    "source_id": "ndtv_hindi_rss",
    "start_time_ist": "03-03-2026 15:34 IST",
    "end_time_ist": "03-03-2026 15:34 IST",
    "records_fetched": 0,
    "failures": 1,
    "error_message": "HTTP Error 403: Forbidden",
    "status": "Fail"
  },
  {
    "fetch_id": "c14f2962",
    "source_id": "bhaskar_biz_rss",
    "start_time_ist": "03-03-2026 15:34 IST",
    "end_time_ist": "03-03-2026 15:34 IST",
    "records_fetched": 0,
    "failures": 0,
    "error_message": "",
    "status": "OK"
  },
  {
    "fetch_id": "7fafc385",
    "source_id": "oilprice_rss",
    "start_time_ist": "03-03-2026 15:35 IST",
    "end_time_ist": "03-03-2026 15:35 IST",
    "records_fetched": 0,
    "failures": 0,
    "error_message": "",
    "status": "OK"
  },
  {
    "fetch_id": "f5a3d12c",
    "source_id": "eia_rss",
    "start_time_ist": "03-03-2026 15:35 IST",
    "end_time_ist": "03-03-2026 15:35 IST",
    "records_fetched": 0,
    "failures": 0,
    "error_message": "",
    "status": "OK"
  },
  {
    "fetch_id": "cc123db5",
    "source_id": "rigzone_rss",
    "start_time_ist": "03-03-2026 15:35 IST",
    "end_time_ist": "03-03-2026 15:35 IST",
    "records_fetched": 0,
    "failures": 0,
    "error_message": "",
    "status": "OK"
  },
  {
    "fetch_id": "5a618ff8",
    "source_id": "reuters_biz_rss",
    "start_time_ist": "03-03-2026 15:35 IST",
    "end_time_ist": "03-03-2026 15:35 IST",
    "records_fetched": 0,
    "failures": 1,
    "error_message": "<urlopen error [Errno 11001] getaddrinfo failed>",
    "status": "Fail"
  },
  {
    "fetch_id": "18a38caa",
    "source_id": "cnbc_energy_rss",
    "start_time_ist": "03-03-2026 15:35 IST",
    "end_time_ist": "03-03-2026 15:35 IST",
    "records_fetched": 0,
    "failures": 0,
    "error_message": "",
    "status": "OK"
  },
  {
    "fetch_id": "a520253a",
    "source_id": "mw_commodities_rss",
    "start_time_ist": "03-03-2026 15:35 IST",
    "end_time_ist": "03-03-2026 15:35 IST",
    "records_fetched": 0,
    "failures": 1,
    "error_message": "HTTP Error 403: Forbidden",
    "status": "Fail"
  },
  {
    "fetch_id": "e52967dc",
    "source_id": "pib_infra_rss",
    "start_time_ist": "03-03-2026 15:35 IST",
    "end_time_ist": "03-03-2026 15:35 IST",
    "records_fetched": 0,
    "failures": 0,
    "error_message": "",
    "status": "OK"
  },
  {
    "fetch_id": "76b21890",
    "source_id": "et_infra_rss",
    "start_time_ist": "03-03-2026 15:35 IST",
    "end_time_ist": "03-03-2026 15:35 IST",
    "records_fetched": 0,
    "failures": 0,
    "error_message": "",
    "status": "OK"
  },
  {
    "fetch_id": "725f1188",
    "source_id": "bs_economy_rss",
    "start_time_ist": "03-03-2026 15:35 IST",
    "end_time_ist": "03-03-2026 15:35 IST",
    "records_fetched": 0,
    "failures": 1,
    "error_message": "HTTP Error 403: Forbidden",
    "status": "Fail"
  },
  {
    "fetch_id": "f0200f3e",
    "source_id": "oilprice_rss",
    "start_time_ist": "03-03-2026 15:35 IST",
    "end_time_ist": "03-03-2026 15:35 IST",
    "records_fetched": 0,
    "failures": 0,
    "error_message": "",
    "status": "OK"
  },
  {
    "fetch_id": "82db201b",
    "source_id": "mint_rss",
    "start_time_ist": "03-03-2026 15:35 IST",
    "end_time_ist": "03-03-2026 15:35 IST",
    "records_fetched": 0,
    "failures": 0,
    "error_message": "",
    "status": "OK"
  },
  {
    "fetch_id": "247c6dea",
    "source_id": "ndtv_hindi_rss",
    "start_time_ist": "03-03-2026 15:35 IST",
    "end_time_ist": "03-03-2026 15:35 IST",
    "records_fetched": 0,
    "failures": 1,
    "error_message": "HTTP Error 403: Forbidden",
    "status": "Fail"
  },
  {
    "fetch_id": "b0f2a129",
    "source_id": "bhaskar_biz_rss",
    "start_time_ist": "03-03-2026 15:35 IST",
    "end_time_ist": "03-03-2026 15:35 IST",
    "records_fetched": 0,
    "failures": 0,
    "error_message": "",
    "status": "OK"
  },
  {
    "fetch_id": "622a68b0",
    "source_id": "eia_rss",
    "start_time_ist": "03-03-2026 15:35 IST",
    "end_time_ist": "03-03-2026 15:35 IST",
    "records_fetched": 0,
    "failures": 0,
    "error_message": "",
    "status": "OK"
  },
  {
    "fetch_id": "11d81c8e",
    "source_id": "rigzone_rss",
    "start_time_ist": "03-03-2026 15:35 IST",
    "end_time_ist": "03-03-2026 15:35 IST",
    "records_fetched": 0,
    "failures": 0,
    "error_message": "",
    "status": "OK"
  },
  {
    "fetch_id": "0cecab4c",
    "source_id": "reuters_biz_rss",
    "start_time_ist": "03-03-2026 15:35 IST",
    "end_time_ist": "03-03-2026 15:35 IST",
    "records_fetched": 0,
    "failures": 1,
    "error_message": "<urlopen error [Errno 11001] getaddrinfo failed>",
    "status": "Fail"
  },
  {
    "fetch_id": "b4c517cd",
    "source_id": "cnbc_energy_rss",
    "start_time_ist": "03-03-2026 15:36 IST",
    "end_time_ist": "03-03-2026 15:36 IST",
    "records_fetched": 0,
    "failures": 0,
    "error_message": "",
    "status": "OK"
  },
  {
    "fetch_id": "50a6b938",
    "source_id": "mw_commodities_rss",
    "start_time_ist": "03-03-2026 15:36 IST",
    "end_time_ist": "03-03-2026 15:36 IST",
    "records_fetched": 0,
    "failures": 1,
    "error_message": "HTTP Error 403: Forbidden",
    "status": "Fail"
  },
  {
    "fetch_id": "b99a524e",
    "source_id": "oilprice_rss",
    "start_time_ist": "03-03-2026 15:36 IST",
    "end_time_ist": "03-03-2026 15:36 IST",
    "records_fetched": 0,
    "failures": 0,
    "error_message": "",
    "status": "OK"
  },
  {
    "fetch_id": "2029f7d8",
    "source_id": "pib_infra_rss",
    "start_time_ist": "03-03-2026 15:36 IST",
    "end_time_ist": "03-03-2026 15:36 IST",
    "records_fetched": 0,
    "failures": 0,
    "error_message": "",
    "status": "OK"
  },
  {
    "fetch_id": "ca1da5a7",
    "source_id": "et_infra_rss",
    "start_time_ist": "03-03-2026 15:36 IST",
    "end_time_ist": "03-03-2026 15:36 IST",
    "records_fetched": 0,
    "failures": 0,
    "error_message": "",
    "status": "OK"
  },
  {
    "fetch_id": "9288d5a6",
    "source_id": "bs_economy_rss",
    "start_time_ist": "03-03-2026 15:36 IST",
    "end_time_ist": "03-03-2026 15:36 IST",
    "records_fetched": 0,
    "failures": 1,
    "error_message": "HTTP Error 403: Forbidden",
    "status": "Fail"
  },
  {
    "fetch_id": "c3bbf166",
    "source_id": "mint_rss",
    "start_time_ist": "03-03-2026 15:36 IST",
    "end_time_ist": "03-03-2026 15:36 IST",
    "records_fetched": 0,
    "failures": 0,
    "error_message": "",
    "status": "OK"
  },
  {
    "fetch_id": "f9ac54cc",
    "source_id": "ndtv_hindi_rss",
    "start_time_ist": "03-03-2026 15:36 IST",
    "end_time_ist": "03-03-2026 15:36 IST",
    "records_fetched": 0,
    "failures": 1,
    "error_message": "HTTP Error 403: Forbidden",
    "status": "Fail"
  },
  {
    "fetch_id": "b6d9841b",
    "source_id": "bhaskar_biz_rss",
    "start_time_ist": "03-03-2026 15:36 IST",
    "end_time_ist": "03-03-2026 15:36 IST",
    "records_fetched": 0,
    "failures": 0,
    "error_message": "",
    "status": "OK"
  },
  {
    "fetch_id": "221a618f",
    "source_id": "rigzone_rss",
    "start_time_ist": "03-03-2026 15:36 IST",
    "end_time_ist": "03-03-2026 15:36 IST",
    "records_fetched": 0,
    "failures": 0,
    "error_message": "",
    "status": "OK"
  },
  {
    "fetch_id": "5ce32b60",
    "source_id": "reuters_biz_rss",
    "start_time_ist": "03-03-2026 15:36 IST",
    "end_time_ist": "03-03-2026 15:36 IST",
    "records_fetched": 0,
    "failures": 1,
    "error_message": "<urlopen error [Errno 11001] getaddrinfo failed>",
    "status": "Fail"
  },
  {
    "fetch_id": "f76e04e9",
    "source_id": "cnbc_energy_rss",
    "start_time_ist": "03-03-2026 15:36 IST",
    "end_time_ist": "03-03-2026 15:36 IST",
    "records_fetched": 0,
    "failures": 0,
    "error_message": "",
    "status": "OK"
  },
  {
    "fetch_id": "f714f1cb",
    "source_id": "mw_commodities_rss",
    "start_time_ist": "03-03-2026 15:36 IST",
    "end_time_ist": "03-03-2026 15:36 IST",
    "records_fetched": 0,
    "failures": 1,
    "error_message": "HTTP Error 403: Forbidden",
    "status": "Fail"
  },
  {
    "fetch_id": "9ca2d919",
    "source_id": "pib_infra_rss",
    "start_time_ist": "03-03-2026 15:36 IST",
    "end_time_ist": "03-03-2026 15:36 IST",
    "records_fetched": 0,
    "failures": 0,
    "error_message": "",
    "status": "OK"
  },
  {
    "fetch_id": "2d954729",
    "source_id": "et_infra_rss",
    "start_time_ist": "03-03-2026 15:36 IST",
    "end_time_ist": "03-03-2026 15:36 IST",
    "records_fetched": 0,
    "failures": 0,
    "error_message": "",
    "status": "OK"
  },
  {
    "fetch_id": "a8f8c56c",
    "source_id": "bs_economy_rss",
    "start_time_ist": "03-03-2026 15:36 IST",
    "end_time_ist": "03-03-2026 15:36 IST",
    "records_fetched": 0,
    "failures": 1,
    "error_message": "HTTP Error 403: Forbidden",
    "status": "Fail"
  },
  {
    "fetch_id": "a32c4601",
    "source_id": "mint_rss",
    "start_time_ist": "03-03-2026 15:36 IST",
    "end_time_ist": "03-03-2026 15:36 IST",
    "records_fetched": 0,
    "failures": 0,
    "error_message": "",
    "status": "OK"
  },
  {
    "fetch_id": "09ccec9b",
    "source_id": "ndtv_hindi_rss",
    "start_time_ist": "03-03-2026 15:36 IST",
    "end_time_ist": "03-03-2026 15:36 IST",
    "records_fetched": 0,
    "failures": 1,
    "error_message": "HTTP Error 403: Forbidden",
    "status": "Fail"
  },
  {
    "fetch_id": "d9671717",
    "source_id": "bhaskar_biz_rss",
    "start_time_ist": "03-03-2026 15:36 IST",
    "end_time_ist": "03-03-2026 15:36 IST",
    "records_fetched": 0,
    "failures": 0,
    "error_message": "",
    "status": "OK"
  },
  {
    "fetch_id": "95afe0c4",
    "source_id": "oilprice_rss",
    "start_time_ist": "03-03-2026 15:44 IST",
    "end_time_ist": "03-03-2026 15:44 IST",
    "records_fetched": 1,
    "failures": 0,
    "error_message": "",
    "status": "OK"
  },
  {
    "fetch_id": "5ca04736",
    "source_id": "eia_rss",
    "start_time_ist": "03-03-2026 15:44 IST",
    "end_time_ist": "03-03-2026 15:44 IST",
    "records_fetched": 0,
    "failures": 0,
    "error_message": "",
    "status": "OK"
  },
  {
    "fetch_id": "45f52ebe",
    "source_id": "rigzone_rss",
    "start_time_ist": "03-03-2026 15:44 IST",
    "end_time_ist": "03-03-2026 15:44 IST",
    "records_fetched": 0,
    "failures": 0,
    "error_message": "",
    "status": "OK"
  },
  {
    "fetch_id": "d0425cae",
    "source_id": "reuters_biz_rss",
    "start_time_ist": "03-03-2026 15:44 IST",
    "end_time_ist": "03-03-2026 15:44 IST",
    "records_fetched": 0,
    "failures": 1,
    "error_message": "<urlopen error [Errno 11001] getaddrinfo failed>",
    "status": "Fail"
  },
  {
    "fetch_id": "910fc11b",
    "source_id": "cnbc_energy_rss",
    "start_time_ist": "03-03-2026 15:44 IST",
    "end_time_ist": "03-03-2026 15:44 IST",
    "records_fetched": 0,
    "failures": 0,
    "error_message": "",
    "status": "OK"
  },
  {
    "fetch_id": "c15732cf",
    "source_id": "mw_commodities_rss",
    "start_time_ist": "03-03-2026 15:44 IST",
    "end_time_ist": "03-03-2026 15:44 IST",
    "records_fetched": 0,
    "failures": 1,
    "error_message": "HTTP Error 403: Forbidden",
    "status": "Fail"
  },
  {
    "fetch_id": "93e086b0",
    "source_id": "pib_infra_rss",
    "start_time_ist": "03-03-2026 15:44 IST",
    "end_time_ist": "03-03-2026 15:44 IST",
    "records_fetched": 0,
    "failures": 0,
    "error_message": "",
    "status": "OK"
  },
  {
    "fetch_id": "320deac1",
    "source_id": "et_infra_rss",
    "start_time_ist": "03-03-2026 15:44 IST",
    "end_time_ist": "03-03-2026 15:44 IST",
    "records_fetched": 0,
    "failures": 0,
    "error_message": "",
    "status": "OK"
  },
  {
    "fetch_id": "7df33a0c",
    "source_id": "bs_economy_rss",
    "start_time_ist": "03-03-2026 15:44 IST",
    "end_time_ist": "03-03-2026 15:44 IST",
    "records_fetched": 0,
    "failures": 1,
    "error_message": "HTTP Error 403: Forbidden",
    "status": "Fail"
  },
  {
    "fetch_id": "20746613",
    "source_id": "mint_rss",
    "start_time_ist": "03-03-2026 15:44 IST",
    "end_time_ist": "03-03-2026 15:44 IST",
    "records_fetched": 0,
    "failures": 0,
    "error_message": "",
    "status": "OK"
  },
  {
    "fetch_id": "58a996ae",
    "source_id": "ndtv_hindi_rss",
    "start_time_ist": "03-03-2026 15:45 IST",
    "end_time_ist": "03-03-2026 15:45 IST",
    "records_fetched": 0,
    "failures": 1,
    "error_message": "HTTP Error 403: Forbidden",
    "status": "Fail"
  },
  {
    "fetch_id": "a0a79148",
    "source_id": "bhaskar_biz_rss",
    "start_time_ist": "03-03-2026 15:45 IST",
    "end_time_ist": "03-03-2026 15:45 IST",
    "records_fetched": 0,
    "failures": 0,
    "error_message": "",
    "status": "OK"
  }
]